httpwaiter/__init__.py
httpwaiter-0.0.0.dist-info/METADATA
httpwaiter-0.0.0.dist-info/WHEEL
httpwaiter-0.0.0.dist-info/top_level.txt
httpwaiter-0.0.0.dist-info/RECORD
