Metadata-Version: 2.1
Name: httpwaiter
Version: 0.0.0
Summary: HTTP Waiter Package
Author-email: Sophia Roger Hürzeler <srh@srhuerzeler.net>
